scatterpy/__init__.py
scatterpy/diameters.py
scatterpy/matstack.py
scatterpy/orientation.py
scatterpy/shapes.py
scatterpy/special.py
scatterpy/tmatrix.py
scatterpy-0.1.1.dist-info/LICENCE
scatterpy-0.1.1.dist-info/METADATA
scatterpy-0.1.1.dist-info/WHEEL
scatterpy-0.1.1.dist-info/top_level.txt
scatterpy-0.1.1.dist-info/RECORD
