Metadata-Version: 2.1
Name: scatterpy
Version: 0.1.1
Summary: Electromagnetic scattering using T-matrix approach
Home-page: https://github.com/TCvanLeth/ScatterPy
Author: T.C. van Leth
Author-email: tommy.vanleth@wur.nl
License: UNKNOWN
Platform: UNKNOWN
Classifier: Programming Language :: Python :: 3
Classifier: License :: OSI Approved :: GNU General Public License v3 or later (GPLv3+)
Classifier: Operating System :: OS Independent
Requires-Dist: numpy
Requires-Dist: scipy
